{"title": "Q8_3 How would you rate the quality of mental health services based on your own experience or that of others you know? After the COVID-19 pandemic", "data": [{"0": 0.0, "Base: Total": 26501.0, "Base: Weighted Total": 26501.0, "0 - Poor": 1930.0, "1": 823.0, "2": 1621.0, "3": 2400.0, "4": 2375.0, "5": 4058.0, "6": 3453.0, "7": 3006.0, "8": 1903.0, "9": 785.0, "10 - Excellent": 742.0, "Not applicable": 893.0, "Don't know": 2513.0, "Total '0 - 3'": 6774.0, "Total '4 - 6'": 9886.0, "Total '7 - 10'": 6436.0, "PAIS": "EU27"}, {"0": "(AB) (AC) (AD) (AE) (AF) (AG) (AH) (AI) (AJ) (AK) (AL) (AM) (AN) (AO) (AP) (AQ) (AT) (AU) (AV) (AW) (AX) (AY) (AZ) (BA)", "Base: Total": 1053, "Base: Weighted Total": 1053, "0 - Poor": 30, "1": 13, "2": 22, "3": 57, "4": 74, "5": 163, "6": 166, "7": 208, "8": 133, "9": 37, "10 - Excellent": 23, "Not applicable": 29, "Don't know": 97, "Total '0 - 3'": 123, "Total '4 - 6'": 404, "Total '7 - 10'": 401, "PAIS": "BE"}, {"0": 0, "Base: Total": 1030, "Base: Weighted Total": 1030, "0 - Poor": 96, "1": 52, "2": 98, "3": 146, "4": 115, "5": 162, "6": 105, "7": 63, "8": 47, "9": 29, "10 - Excellent": 32, "Not applicable": 13, "Don't know": 73, "Total '0 - 3'": 391, "Total '4 - 6'": 382, "Total '7 - 10'": 171, "PAIS": "BG"}, {"0": "(AB) (AF) (AG) (AH) (AI) (AJ) (AK) (AM) (AN) (AP) (AQ) (AU) (AX) (AY) (BA)", "Base: Total": 1042, "Base: Weighted Total": 1042, "0 - Poor": 48, "1": 31, "2": 55, "3": 95, "4": 101, "5": 179, "6": 155, "7": 129, "8": 95, "9": 39, "10 - Excellent": 31, "Not applicable": 13, "Don't know": 71, "Total '0 - 3'": 229, "Total '4 - 6'": 434, "Total '7 - 10'": 294, "PAIS": "CZ"}, {"0": "(AB) (AF) (AG) (AH) (AI) (AJ) (AM) (AN) (AQ) (AU) (AY) (BA)", "Base: Total": 1035, "Base: Weighted Total": 1035, "0 - Poor": 34, "1": 24, "2": 53, "3": 93, "4": 100, "5": 164, "6": 139, "7": 128, "8": 86, "9": 28, "10 - Excellent": 36, "Not applicable": 40, "Don't know": 110, "Total '0 - 3'": 204, "Total '4 - 6'": 404, "Total '7 - 10'": 277, "PAIS": "DK"}, {"0": "(AB) (AG) (AH) (AI) (AJ) (AM) (AN) (AQ) (AU) (BA)", "Base: Total": 1021, "Base: Weighted Total": 1021, "0 - Poor": 53, "1": 24, "2": 73, "3": 98, "4": 95, "5": 174, "6": 117, "7": 110, "8": 71, "9": 34, "10 - Excellent": 47, "Not applicable": 30, "Don't know": 94, "Total '0 - 3'": 249, "Total '4 - 6'": 386, "Total '7 - 10'": 262, "PAIS": "DE"}, {"0": "(AB) (AQ) (BA)", "Base: Total": 1035, "Base: Weighted Total": 1035, "0 - Poor": 44, "1": 31, "2": 47, "3": 77, "4": 96, "5": 148, "6": 114, "7": 100, "8": 74, "9": 29, "10 - Excellent": 28, "Not applicable": 83, "Don't know": 164, "Total '0 - 3'": 199, "Total '4 - 6'": 358, "Total '7 - 10'": 231, "PAIS": "EE"}, {"0": "(AB) (AQ)", "Base: Total": 1049, "Base: Weighted Total": 1049, "0 - Poor": 108, "1": 45, "2": 93, "3": 107, "4": 116, "5": 141, "6": 122, "7": 95, "8": 69, "9": 26, "10 - Excellent": 35, "Not applicable": 31, "Don't know": 60, "Total '0 - 3'": 354, "Total '4 - 6'": 379, "Total '7 - 10'": 225, "PAIS": "IE"}, {"0": "(AB) (AQ)", "Base: Total": 1064, "Base: Weighted Total": 1064, "0 - Poor": 136, "1": 55, "2": 67, "3": 106, "4": 103, "5": 157, "6": 119, "7": 103, "8": 72, "9": 33, "10 - Excellent": 18, "Not applicable": 15, "Don't know": 80, "Total '0 - 3'": 363, "Total '4 - 6'": 379, "Total '7 - 10'": 226, "PAIS": "EL"}, {"0": 0, "Base: Total": 1014, "Base: Weighted Total": 1014, "0 - Poor": 139, "1": 49, "2": 64, "3": 99, "4": 99, "5": 147, "6": 113, "7": 105, "8": 58, "9": 17, "10 - Excellent": 16, "Not applicable": 35, "Don't know": 74, "Total '0 - 3'": 351, "Total '4 - 6'": 358, "Total '7 - 10'": 196, "PAIS": "ES"}, {"0": "(AB) (AQ) (BA)", "Base: Total": 1042, "Base: Weighted Total": 1042, "0 - Poor": 80, "1": 33, "2": 81, "3": 113, "4": 90, "5": 155, "6": 116, "7": 117, "8": 64, "9": 24, "10 - Excellent": 24, "Not applicable": 26, "Don't know": 119, "Total '0 - 3'": 308, "Total '4 - 6'": 361, "Total '7 - 10'": 228, "PAIS": "FR"}, {"0": "(AB) (AI) (AM) (AQ) (BA)", "Base: Total": 1003, "Base: Weighted Total": 1003, "0 - Poor": 51, "1": 46, "2": 69, "3": 104, "4": 120, "5": 172, "6": 138, "7": 101, "8": 80, "9": 30, "10 - Excellent": 27, "Not applicable": 23, "Don't know": 44, "Total '0 - 3'": 269, "Total '4 - 6'": 429, "Total '7 - 10'": 238, "PAIS": "HR"}, {"0": "(AB) (AG) (AH) (AI) (AJ) (AM) (AN) (AQ) (AU) (BA)", "Base: Total": 1027, "Base: Weighted Total": 1027, "0 - Poor": 63, "1": 18, "2": 37, "3": 57, "4": 83, "5": 167, "6": 190, "7": 124, "8": 86, "9": 35, "10 - Excellent": 20, "Not applicable": 42, "Don't know": 107, "Total '0 - 3'": 175, "Total '4 - 6'": 440, "Total '7 - 10'": 264, "PAIS": "IT"}, {"0": 0, "Base: Total": 544, "Base: Weighted Total": 544, "0 - Poor": 32, "1": 19, "2": 45, "3": 56, "4": 58, "5": 89, "6": 75, "7": 51, "8": 26, "9": 7, "10 - Excellent": 15, "Not applicable": 3, "Don't know": 68, "Total '0 - 3'": 152, "Total '4 - 6'": 222, "Total '7 - 10'": 99, "PAIS": "CY"}, {"0": 0, "Base: Total": 1051, "Base: Weighted Total": 1051, "0 - Poor": 61, "1": 27, "2": 57, "3": 86, "4": 102, "5": 168, "6": 135, "7": 115, "8": 56, "9": 21, "10 - Excellent": 18, "Not applicable": 57, "Don't know": 149, "Total '0 - 3'": 231, "Total '4 - 6'": 405, "Total '7 - 10'": 210, "PAIS": "LV"}, {"0": "(AB) (AF) (AG) (AH) (AI) (AJ) (AK) (AM) (AN) (AP) (AQ) (AU) (AY) (BA)", "Base: Total": 1078, "Base: Weighted Total": 1078, "0 - Poor": 47, "1": 27, "2": 46, "3": 94, "4": 87, "5": 191, "6": 153, "7": 146, "8": 94, "9": 23, "10 - Excellent": 39, "Not applicable": 15, "Don't know": 116, "Total '0 - 3'": 214, "Total '4 - 6'": 431, "Total '7 - 10'": 302, "PAIS": "LT"}, {"0": "(AB) (AQ)", "Base: Total": 544, "Base: Weighted Total": 544, "0 - Poor": 25, "1": 6, "2": 17, "3": 40, "4": 50, "5": 74, "6": 81, "7": 59, "8": 42, "9": 10, "10 - Excellent": 9, "Not applicable": 22, "Don't know": 110, "Total '0 - 3'": 87, "Total '4 - 6'": 206, "Total '7 - 10'": 120, "PAIS": "LU"}, {"0": 0, "Base: Total": 1039, "Base: Weighted Total": 1039, "0 - Poor": 142, "1": 49, "2": 71, "3": 145, "4": 102, "5": 161, "6": 105, "7": 75, "8": 51, "9": 15, "10 - Excellent": 32, "Not applicable": 13, "Don't know": 76, "Total '0 - 3'": 409, "Total '4 - 6'": 368, "Total '7 - 10'": 173, "PAIS": "HU"}, {"0": "(AB) (AC) (AD) (AE) (AF) (AG) (AH) (AI) (AJ) (AK) (AL) (AM) (AN) (AO) (AP) (AQ) (AT) (AU) (AV) (AW) (AX) (AY) (AZ) (BA)", "Base: Total": 517, "Base: Weighted Total": 517, "0 - Poor": 15, "1": 4, "2": 20, "3": 25, "4": 37, "5": 83, "6": 73, "7": 89, "8": 55, "9": 17, "10 - Excellent": 23, "Not applicable": 21, "Don't know": 53, "Total '0 - 3'": 65, "Total '4 - 6'": 193, "Total '7 - 10'": 184, "PAIS": "MT"}, {"0": "(AB) (AC) (AD) (AE) (AF) (AG) (AH) (AI) (AJ) (AK) (AL) (AM) (AN) (AO) (AP) (AQ) (AT) (AU) (AV) (AW) (AX) (AY) (AZ) (BA)", "Base: Total": 1048, "Base: Weighted Total": 1048, "0 - Poor": 17, "1": 18, "2": 26, "3": 58, "4": 75, "5": 117, "6": 195, "7": 212, "8": 134, "9": 32, "10 - Excellent": 18, "Not applicable": 46, "Don't know": 99, "Total '0 - 3'": 119, "Total '4 - 6'": 387, "Total '7 - 10'": 396, "PAIS": "NL"}, {"0": "(AB) (AG) (AH) (AI) (AM) (AN) (AQ) (AU) (BA)", "Base: Total": 1038, "Base: Weighted Total": 1038, "0 - Poor": 63, "1": 29, "2": 60, "3": 107, "4": 106, "5": 205, "6": 118, "7": 105, "8": 77, "9": 44, "10 - Excellent": 39, "Not applicable": 21, "Don't know": 63, "Total '0 - 3'": 260, "Total '4 - 6'": 429, "Total '7 - 10'": 266, "PAIS": "AT"}, {"0": "(AB) (AQ)", "Base: Total": 1051, "Base: Weighted Total": 1051, "0 - Poor": 88, "1": 47, "2": 71, "3": 101, "4": 89, "5": 139, "6": 135, "7": 100, "8": 56, "9": 36, "10 - Excellent": 26, "Not applicable": 79, "Don't know": 85, "Total '0 - 3'": 308, "Total '4 - 6'": 362, "Total '7 - 10'": 218, "PAIS": "PL"}, {"0": "(AB) (AI) (AM) (AN) (AQ) (AU) (BA)", "Base: Total": 1021, "Base: Weighted Total": 1021, "0 - Poor": 60, "1": 42, "2": 66, "3": 97, "4": 102, "5": 163, "6": 149, "7": 133, "8": 79, "9": 20, "10 - Excellent": 20, "Not applicable": 15, "Don't know": 74, "Total '0 - 3'": 265, "Total '4 - 6'": 414, "Total '7 - 10'": 253, "PAIS": "PT"}, {"0": "(AB) (AF) (AG) (AH) (AI) (AJ) (AK) (AM) (AN) (AP) (AQ) (AU) (AV) (AX) (AY) (BA)", "Base: Total": 1023, "Base: Weighted Total": 1023, "0 - Poor": 83, "1": 35, "2": 69, "3": 92, "4": 82, "5": 125, "6": 112, "7": 109, "8": 91, "9": 54, "10 - Excellent": 48, "Not applicable": 31, "Don't know": 92, "Total '0 - 3'": 279, "Total '4 - 6'": 319, "Total '7 - 10'": 302, "PAIS": "RO"}, {"0": "(AB) (AI) (AM) (AN) (AQ) (BA)", "Base: Total": 1030, "Base: Weighted Total": 1030, "0 - Poor": 59, "1": 39, "2": 72, "3": 94, "4": 116, "5": 142, "6": 145, "7": 114, "8": 80, "9": 32, "10 - Excellent": 21, "Not applicable": 22, "Don't know": 94, "Total '0 - 3'": 264, "Total '4 - 6'": 403, "Total '7 - 10'": 247, "PAIS": "SI"}, {"0": "(AB) (AQ) (BA)", "Base: Total": 1028, "Base: Weighted Total": 1028, "0 - Poor": 84, "1": 28, "2": 65, "3": 85, "4": 106, "5": 195, "6": 112, "7": 99, "8": 63, "9": 27, "10 - Excellent": 40, "Not applicable": 64, "Don't know": 58, "Total '0 - 3'": 263, "Total '4 - 6'": 413, "Total '7 - 10'": 230, "PAIS": "SK"}, {"0": "(AB) (AG) (AH) (AI) (AJ) (AM) (AN) (AQ) (AU) (BA)", "Base: Total": 1047, "Base: Weighted Total": 1047, "0 - Poor": 44, "1": 23, "2": 67, "3": 91, "4": 111, "5": 169, "6": 152, "7": 147, "8": 81, "9": 25, "10 - Excellent": 18, "Not applicable": 17, "Don't know": 99, "Total '0 - 3'": 225, "Total '4 - 6'": 433, "Total '7 - 10'": 272, "PAIS": "FI"}, {"0": 0, "Base: Total": 1027, "Base: Weighted Total": 1027, "0 - Poor": 46, "1": 19, "2": 55, "3": 85, "4": 87, "5": 133, "6": 112, "7": 86, "8": 54, "9": 21, "10 - Excellent": 24, "Not applicable": 30, "Don't know": 274, "Total '0 - 3'": 205, "Total '4 - 6'": 333, "Total '7 - 10'": 185, "PAIS": "SE"}]}